flake8_secure_coding_standard.py
flake8_secure_coding_standard-1.4.1.dist-info/LICENSE
flake8_secure_coding_standard-1.4.1.dist-info/METADATA
flake8_secure_coding_standard-1.4.1.dist-info/WHEEL
flake8_secure_coding_standard-1.4.1.dist-info/entry_points.txt
flake8_secure_coding_standard-1.4.1.dist-info/top_level.txt
flake8_secure_coding_standard-1.4.1.dist-info/RECORD
