Metadata-Version: 2.1
Name: flake8-secure-coding-standard
Version: 1.4.1
Summary: Flake8 plugin adding some checks to make Python code adhere to more secure coding standard
Home-page: https://github.com/Takishima/flake8-secure-coding-standard
Author: Damien Nguyen
Author-email: ngn.damien@gmail.com
License: Apache2
Classifier: License :: OSI Approved :: Apache Software License
Classifier: Programming Language :: Python :: 3
Classifier: Programming Language :: Python :: 3 :: Only
Classifier: Programming Language :: Python :: 3.8
Classifier: Programming Language :: Python :: 3.9
Classifier: Programming Language :: Python :: 3.10
Classifier: Programming Language :: Python :: 3.11
Requires-Python: >=3.8
License-File: LICENSE
Requires-Dist: flake8<8.0,>=3.7
Provides-Extra: test
Requires-Dist: mock; extra == "test"
Requires-Dist: pytest; extra == "test"
Requires-Dist: pytest-cov; extra == "test"
Requires-Dist: pytest-mock; extra == "test"
